agglomerate/__init__.py
agglomerate/agglomerate_3d.py
agglomerate/batch_agglomerate_3d.py
data/__init__.py
data/data_loader.py
data/data_types.py
metrics/__init__.py
metrics/metric_utils.py
3dtrees_nbingo-0.1.5.dist-info/LICENSE.txt
3dtrees_nbingo-0.1.5.dist-info/METADATA
3dtrees_nbingo-0.1.5.dist-info/WHEEL
3dtrees_nbingo-0.1.5.dist-info/top_level.txt
3dtrees_nbingo-0.1.5.dist-info/RECORD
